MANIFEST.in
README.rst
setup.py
django_validated_file.egg-info/PKG-INFO
django_validated_file.egg-info/SOURCES.txt
django_validated_file.egg-info/dependency_links.txt
django_validated_file.egg-info/requires.txt
django_validated_file.egg-info/top_level.txt
testing/__init__.py
testing/forms.py
testing/models.py
testing/settings.py
testing/tests.py
testing/urls.py
validatedfile/__init__.py
validatedfile/fields.py
validatedfile/models.py
validatedfile/locale/en/LC_MESSAGES/django.mo
validatedfile/locale/en/LC_MESSAGES/django.po
validatedfile/locale/es/LC_MESSAGES/django.mo
validatedfile/locale/es/LC_MESSAGES/django.po